laurentpolynomials/__init__.py
laurentpolynomials/laurent_polynomial.py
laurentpolynomials-0.0.1.dist-info/LICENSE
laurentpolynomials-0.0.1.dist-info/METADATA
laurentpolynomials-0.0.1.dist-info/WHEEL
laurentpolynomials-0.0.1.dist-info/top_level.txt
laurentpolynomials-0.0.1.dist-info/RECORD
